arcgen/__init__.py
arcgen/arcgen.py
arcgen/polygonFunctions/__init__.py
arcgen/polygonFunctions/polygonFunctions.py
arcgen/uniquetol/__init__.py
arcgen/uniquetol/uniquetol.py
arcgen_python-2024.1.0.dist-info/METADATA
arcgen_python-2024.1.0.dist-info/WHEEL
arcgen_python-2024.1.0.dist-info/licenses/LICENSE
arcgen_python-2024.1.0.dist-info/RECORD
