Metadata-Version: 2.3
Name: arcgen-python
Version: 2024.1.0
Summary: Arc-length Response Corridor Generation
Project-URL: Homepage, https://github.com/IMMC-UWaterloo/ARCGen-Python
Project-URL: Documentation, https://github.com/IMMC-UWaterloo/ARCGen-Python
Project-URL: Repository, https://github.com/IMMC-UWaterloo/ARCGen-Python.git
Project-URL: Issues, https://github.com/IMMC-UWaterloo/ARCGen-Python/issues
Author-email: Devon Hartlen <hartlendc@gmail.com>
License:                     GNU GENERAL PUBLIC LICENSE
Keywords: arc-length,averaging,corridors,response corridors,statistics
Classifier: Development Status :: 5 - Production/Stable
Classifier: Intended Audience :: Science/Research
Classifier: License :: OSI Approved :: GNU General Public License v3 (GPLv3)
Classifier: Programming Language :: Python :: 3.10
Classifier: Programming Language :: Python :: 3.11
Classifier: Programming Language :: Python :: 3.12
Classifier: Topic :: Scientific/Engineering
Requires-Python: >=3.10
Requires-Dist: matplotlib>=3.9.2
Requires-Dist: numpy>=2.1.3
Requires-Dist: scipy>=1.14.1
